app/__init__.py
app/__main__.py
app/config.py
app/agents/__init__.py
app/agents/agent.py
app/models/__init__.py
app/models/llm_factory.py
app/services/__init__.py
app/services/git_service.py
app/services/summarize_service.py
app/telemetry/__init__.py
app/telemetry/setup.py
autoreporeview-0.1.2.dist-info/METADATA
autoreporeview-0.1.2.dist-info/WHEEL
autoreporeview-0.1.2.dist-info/entry_points.txt
autoreporeview-0.1.2.dist-info/licenses/LICENSE.md
autoreporeview-0.1.2.dist-info/RECORD
