Metadata-Version: 2.4
Name: autoreporeview
Version: 0.1.2
Summary: AI-powered git repository change analysis tool
Author: AutoRepoReview Team
License: MIT
License-File: LICENSE.md
Keywords: ai,code-analysis,diff-summary,git,repository-review
Classifier: Development Status :: 3 - Alpha
Classifier: Intended Audience :: Developers
Classifier: License :: OSI Approved :: MIT License
Classifier: Programming Language :: Python :: 3
Classifier: Programming Language :: Python :: 3.13
Classifier: Topic :: Software Development :: Quality Assurance
Classifier: Topic :: Software Development :: Version Control :: Git
Requires-Python: >=3.13
Requires-Dist: keyring>=25.0.0
Requires-Dist: langchain-gigachat>=0.3.12
Requires-Dist: langchain-openai>=0.2.0
Requires-Dist: langchain>=0.3.27
Requires-Dist: langgraph>=1.0.1
Requires-Dist: opentelemetry-api>=1.24.0
Requires-Dist: opentelemetry-exporter-otlp-proto-http>=1.24.0
Requires-Dist: opentelemetry-instrumentation-requests>=0.45b0
Requires-Dist: opentelemetry-instrumentation>=0.45b0
Requires-Dist: opentelemetry-sdk>=1.24.0
Requires-Dist: python-dotenv>=1.2.1
Requires-Dist: tiktoken>=0.12.0
Requires-Dist: typer>=0.20.0
